linemux/__init__.py
linemux/__main__.py
linemux/command.py
linemux-0.2.0.dist-info/LICENSE
linemux-0.2.0.dist-info/METADATA
linemux-0.2.0.dist-info/WHEEL
linemux-0.2.0.dist-info/entry_points.txt
linemux-0.2.0.dist-info/top_level.txt
linemux-0.2.0.dist-info/RECORD
