Metadata-Version: 2.1
Name: linemux
Version: 0.2.0
Summary: File multiplexer
Home-page: https://gitlab.com/cincan/linemux
Author: Rauli Kaksonen
Author-email: rauli.kaksonen@gmail.com
License: UNKNOWN
Platform: UNKNOWN
Classifier: Programming Language :: Python :: 3
Classifier: License :: OSI Approved :: MIT License
Classifier: Operating System :: OS Independent
Requires-Python: >=3.6
